{
    "type": "minecraft:blasting",
    "category": "misc",
    "cookingtime": 100,
    "experience": 0.1,
    "ingredient": [
        "skniro_furniture:cherry_pickaxe",
        "skniro_furniture:cherry_shovel",
        "skniro_furniture:cherry_axe",
        "skniro_furniture:cherry_hoe",
        "skniro_furniture:cherry_sword",
        "skniro_furniture:cherry_helmet",
        "skniro_furniture:cherry_chestplate",
        "skniro_furniture:cherry_leggings",
        "skniro_furniture:cherry_boots"
    ],
    "result": {
        "id":"skniro_furniture:cherry_nugget"
    }
}